lilliepy_statics/__init__.py
lilliepy_statics/main.py
lilliepy_statics-7.0.dist-info/METADATA
lilliepy_statics-7.0.dist-info/WHEEL
lilliepy_statics-7.0.dist-info/top_level.txt
lilliepy_statics-7.0.dist-info/RECORD
