Metadata-Version: 2.2
Name: lilliepy-statics
Version: 7.0
Summary: helps with static files related stuff in the lilliepy framework
Home-page: https://github.com/websitedeb/lilliepy-statics
Author: Sarthak Ghoshal
Author-email: sarthak22.ghoshal@gmail.com
License: MIT
Keywords: lilliepy,lilliepy-static,reactpy,lilliepy-statics
Classifier: Programming Language :: Python :: 3
Classifier: License :: OSI Approved :: MIT License
Classifier: Operating System :: OS Independent
Requires-Python: >=3.6
Requires-Dist: reactpy
Dynamic: author
Dynamic: author-email
Dynamic: classifier
Dynamic: home-page
Dynamic: keywords
Dynamic: license
Dynamic: requires-dist
Dynamic: requires-python
Dynamic: summary
